stb/__init__.py
stb/cli/__init__.py
stb/cli/config.py
stb/cli/press.py
stb/cli/runner.py
stb/config/config.original.toml
stb/core/__init__.py
stb/core/display.py
stb/core/frame.py
stb/core/key_press.py
stb/remote.py
stb/utils.py
stb_automator-0.1.0.dist-info/entry_points.txt
stb_automator-0.1.0.dist-info/LICENSE
stb_automator-0.1.0.dist-info/WHEEL
stb_automator-0.1.0.dist-info/METADATA
stb_automator-0.1.0.dist-info/RECORD
