Metadata-Version: 2.1
Name: stb-automator
Version: 0.1.0
Summary: A library for automated control & testing of set-top boxes
Home-page: https://github.com/eugenetriguba/stb-automator
License: MIT
Keywords: set-top box,test automation,opencv,tesseract,LIRC,gstreamer
Author: Eugene Triguba
Author-email: eugenetriguba@gmail.com
Requires-Python: >=3.7,<4.0
Classifier: Development Status :: 1 - Planning
Classifier: License :: OSI Approved :: MIT License
Classifier: Operating System :: POSIX :: Linux
Classifier: Programming Language :: Python :: 3
Classifier: Programming Language :: Python :: 3.6
Classifier: Programming Language :: Python :: 3.7
Classifier: Programming Language :: Python :: 3.8
Classifier: Programming Language :: Python :: 3.9
Classifier: Topic :: Software Development :: Libraries :: Python Modules
Classifier: Topic :: Software Development :: Testing
Requires-Dist: PyGObject (>=3.40.0,<4.0.0)
Requires-Dist: click (>=7.1.2,<8.0.0)
Requires-Dist: config-file[toml] (>=0.12.0,<0.13.0)
Requires-Dist: lirc (>=1.0.1,<2.0.0)
Requires-Dist: numpy (>=1.20.2,<2.0.0)
Requires-Dist: opencv-python (>=4.5.1,<5.0.0)
Requires-Dist: pytesseract (>=0.3.7,<0.4.0)
Project-URL: Repository, https://github.com/eugenetriguba/stb-automator
